rebasehelper/__init__.py
rebasehelper/application.py
rebasehelper/archive.py
rebasehelper/argument_parser.py
rebasehelper/cli.py
rebasehelper/completion.py
rebasehelper/config.py
rebasehelper/constants.py
rebasehelper/exceptions.py
rebasehelper/logger.py
rebasehelper/options.py
rebasehelper/patcher.py
rebasehelper/results_store.py
rebasehelper/sample_config.py
rebasehelper/specfile.py
rebasehelper/temporary_environment.py
rebasehelper/types.py
rebasehelper/helpers/__init__.py
rebasehelper/helpers/bugzilla_helper.py
rebasehelper/helpers/console_helper.py
rebasehelper/helpers/copr_helper.py
rebasehelper/helpers/download_helper.py
rebasehelper/helpers/git_helper.py
rebasehelper/helpers/input_helper.py
rebasehelper/helpers/koji_helper.py
rebasehelper/helpers/lookaside_cache_helper.py
rebasehelper/helpers/path_helper.py
rebasehelper/helpers/process_helper.py
rebasehelper/helpers/rpm_helper.py
rebasehelper/plugins/__init__.py
rebasehelper/plugins/plugin.py
rebasehelper/plugins/plugin_collection.py
rebasehelper/plugins/plugin_loader.py
rebasehelper/plugins/plugin_manager.py
rebasehelper/plugins/build_log_hooks/__init__.py
rebasehelper/plugins/build_log_hooks/files.py
rebasehelper/plugins/build_tools/__init__.py
rebasehelper/plugins/build_tools/rpm/__init__.py
rebasehelper/plugins/build_tools/rpm/copr_.py
rebasehelper/plugins/build_tools/rpm/koji_.py
rebasehelper/plugins/build_tools/rpm/mock.py
rebasehelper/plugins/build_tools/rpm/rpmbuild.py
rebasehelper/plugins/build_tools/srpm/__init__.py
rebasehelper/plugins/build_tools/srpm/mock.py
rebasehelper/plugins/build_tools/srpm/rpmbuild.py
rebasehelper/plugins/checkers/__init__.py
rebasehelper/plugins/checkers/abipkgdiff.py
rebasehelper/plugins/checkers/csmock.py
rebasehelper/plugins/checkers/licensecheck.py
rebasehelper/plugins/checkers/pkgdiff.py
rebasehelper/plugins/checkers/rpmdiff.py
rebasehelper/plugins/checkers/rpminspect.py
rebasehelper/plugins/checkers/rpminspect_rpm.py
rebasehelper/plugins/checkers/rpminspect_srpm.py
rebasehelper-0.29.6.dist-info/licenses/LICENSE
rebasehelper-0.29.6.dist-info/METADATA
rebasehelper-0.29.6.dist-info/WHEEL
rebasehelper-0.29.6.dist-info/entry_points.txt
rebasehelper-0.29.6.dist-info/top_level.txt
rebasehelper-0.29.6.dist-info/RECORD
