Metadata-Version: 2.4
Name: rebasehelper
Version: 0.29.6
Summary: This tool helps you rebase your package to the latest version.
Home-page: https://github.com/rebase-helper/rebase-helper
Author: Petr Hráček
Author-email: phracek@redhat.com
Maintainer: Nikola Forró
Maintainer-email: nforro@redhat.com
License: GPLv2+
Project-URL: Source Code, https://github.com/rebase-helper/rebase-helper
Project-URL: Documentation, https://rebase-helper.readthedocs.io
Project-URL: Bug Tracker, https://github.com/rebase-helper/rebase-helper/issues
Keywords: rebase,packaging,rpm,spec
Classifier: Development Status :: 4 - Beta
Classifier: Environment :: Console
Classifier: Intended Audience :: Developers
Classifier: License :: OSI Approved :: GNU General Public License v2 or later (GPLv2+)
Classifier: Operating System :: POSIX :: Linux
Classifier: Programming Language :: Python
Classifier: Programming Language :: Python :: 3
Classifier: Programming Language :: Python :: 3 :: Only
Classifier: Programming Language :: Python :: 3.9
Classifier: Programming Language :: Python :: 3.10
Classifier: Programming Language :: Python :: 3.11
Classifier: Topic :: Software Development
Classifier: Topic :: System :: Operating System
Classifier: Topic :: System :: Software Distribution
Classifier: Topic :: Utilities
Requires-Python: >=3.9
License-File: LICENSE
Requires-Dist: copr
Requires-Dist: pyquery
Requires-Dist: python-pam
Requires-Dist: requests
Requires-Dist: rpkg
Requires-Dist: unidiff
Requires-Dist: GitPython
Requires-Dist: specfile
Provides-Extra: testing
Requires-Dist: pytest; extra == "testing"
Dynamic: license-file
